setup.py
pyhosts/__init__.py
pyhosts/host.py
pyhosts.egg-info/PKG-INFO
pyhosts.egg-info/SOURCES.txt
pyhosts.egg-info/dependency_links.txt
pyhosts.egg-info/top_level.txt
test/test_base.py