Metadata-Version: 1.0
Name: pyhosts
Version: 0.1
Summary: Pythonic way to manage hosts file.
Home-page: http://github.com/pletisan/pyhosts/
Author: Igor Milovanovic
Author-email: igor@tnkng.com
License: UNKNOWN
Platform: UNKNOWN
